jax_plugins/metal_plugin/__init__.py
jax_plugins/metal_plugin/pjrt_plugin_metal_14.dylib
jax_metal-0.1.1.dist-info/LICENSE
jax_metal-0.1.1.dist-info/METADATA
jax_metal-0.1.1.dist-info/WHEEL
jax_metal-0.1.1.dist-info/entry_points.txt
jax_metal-0.1.1.dist-info/top_level.txt
jax_metal-0.1.1.dist-info/RECORD
