Metadata-Version: 2.1
Name: jax-metal
Version: 0.1.1
Summary: JAX acceleration for Mac GPUs.
Home-page: https://developer.apple.com/metal/jax/
Download-URL: 
Author: 
Author-email: 
License: Copyright © 2023 Apple Inc. All rights reserved.
Keywords: jax metal plugin
License-File: LICENSE
Requires-Dist: wheel~=0.35
Requires-Dist: six>=1.15.0
Requires-Dist: jaxlib>=0.4.34
Requires-Dist: jax>=0.4.34
